tab2img/__init__.py
tab2img/converter.py
tab2img-0.0.2.dist-info/LICENSE.txt
tab2img-0.0.2.dist-info/METADATA
tab2img-0.0.2.dist-info/WHEEL
tab2img-0.0.2.dist-info/top_level.txt
tab2img-0.0.2.dist-info/RECORD
