Metadata-Version: 2.1
Name: tab2img
Version: 0.0.2
Summary: A tool to convert tabular data into images, in order to be used by CNN. Inspired by the 'DeepInsight' paper.
Home-page: https://github.com/nicomignoni/tab2img
Author: Nicola Mignoni
Author-email: nicola.mignoni@gmail.com
License: UNKNOWN
Platform: UNKNOWN
Classifier: Programming Language :: Python :: 3
Classifier: License :: OSI Approved :: MIT License
Classifier: Operating System :: OS Independent
Requires-Python: >=3.7
